masr/__init__.py
masr/predict.py
masr/trainer.py
masr/configs/augmentation.yml
masr/configs/conformer.yml
masr/configs/decoder.yml
masr/configs/deepspeech2.yml
masr/configs/efficient_conformer.yml
masr/configs/squeezeformer.yml
masr/data_utils/__init__.py
masr/data_utils/audio_featurizer.py
masr/data_utils/binary.py
masr/data_utils/collate_fn.py
masr/data_utils/normalizer.py
masr/data_utils/reader.py
masr/data_utils/sampler.py
masr/data_utils/tokenizer.py
masr/data_utils/utils.py
masr/decoders/__init__.py
masr/decoders/attention_rescoring.py
masr/decoders/beam_search_decoder.py
masr/decoders/ctc_greedy_search.py
masr/decoders/ctc_prefix_beam_search.py
masr/decoders/utils.py
masr/infer_utils/__init__.py
masr/infer_utils/inference_predictor.py
masr/infer_utils/punc_predictor.py
masr/infer_utils/utils.py
masr/model_utils/__init__.py
masr/model_utils/conformer/__init__.py
masr/model_utils/conformer/attention.py
masr/model_utils/conformer/convolution.py
masr/model_utils/conformer/embedding.py
masr/model_utils/conformer/encoder.py
masr/model_utils/conformer/model.py
masr/model_utils/conformer/positionwise.py
masr/model_utils/conformer/subsampling.py
masr/model_utils/deepspeech2/__init__.py
masr/model_utils/deepspeech2/conv.py
masr/model_utils/deepspeech2/encoder.py
masr/model_utils/deepspeech2/gru.py
masr/model_utils/deepspeech2/model.py
masr/model_utils/efficient_conformer/__init__.py
masr/model_utils/efficient_conformer/attention.py
masr/model_utils/efficient_conformer/convolution.py
masr/model_utils/efficient_conformer/encoder.py
masr/model_utils/efficient_conformer/model.py
masr/model_utils/efficient_conformer/subsampling.py
masr/model_utils/loss/__init__.py
masr/model_utils/loss/ctc.py
masr/model_utils/loss/label_smoothing_loss.py
masr/model_utils/squeezeformer/__init__.py
masr/model_utils/squeezeformer/attention.py
masr/model_utils/squeezeformer/conv2d.py
masr/model_utils/squeezeformer/convolution.py
masr/model_utils/squeezeformer/encoder.py
masr-3.0.2.dist-info/LICENSE
masr-3.0.2.dist-info/METADATA
masr-3.0.2.dist-info/WHEEL
masr-3.0.2.dist-info/top_level.txt
masr-3.0.2.dist-info/RECORD
