Metadata-Version: 2.1
Name: masr
Version: 3.0.2
Summary: Automatic speech recognition toolkit on Pytorch
Home-page: https://github.com/yeyupiaoling/MASR
Download-URL: https://github.com/yeyupiaoling/MASR.git
Author: yeyupiaoling
License: Apache License 2.0
Keywords: asr,pytorch
Classifier: Intended Audience :: Developers
Classifier: License :: OSI Approved :: Apache Software License
Classifier: Operating System :: OS Independent
Classifier: Natural Language :: Chinese (Simplified)
Classifier: Programming Language :: Python :: 3
Classifier: Programming Language :: Python :: 3.7
Classifier: Programming Language :: Python :: 3.8
Classifier: Programming Language :: Python :: 3.9
Classifier: Programming Language :: Python :: 3.10
Classifier: Programming Language :: Python :: 3.11
Classifier: Topic :: Utilities
License-File: LICENSE
Requires-Dist: numpy>=1.19.2
Requires-Dist: scipy>=1.6.3
Requires-Dist: python-Levenshtein>=0.25.1
Requires-Dist: visualdl==2.5.3
Requires-Dist: soundfile>=0.12.1
Requires-Dist: soundcard>=0.4.2
Requires-Dist: resampy>=0.2.2
Requires-Dist: zhconv>=1.4.2
Requires-Dist: ijson>=3.1.4
Requires-Dist: pyyaml>=5.4.1
Requires-Dist: scikit-learn>=1.0.2
Requires-Dist: typeguard>=2.13.3
Requires-Dist: onnxruntime>=1.17.1
Requires-Dist: sentencepiece>=0.2.0
Requires-Dist: loguru>=0.7.2
Requires-Dist: yeaudio>=0.0.7
Requires-Dist: kaldi-native-fbank>=1.20.0
Requires-Dist: tqdm
